Metadata-Version: 2.1
Name: oneNeuron-pypi-vkg0312
Version: 0.0.3
Summary: Its a implementation of perceptron
Home-page: https://github.com/vkg0312/oneNeuron_pypi
Author: VARUN
Author-email: vkg0312@gmail.com
License: UNKNOWN
Project-URL: Bug Tracker, https://github.com/vkg0312/oneNeuron_pypi/issues
Platform: UNKNOWN
Classifier: Programming Language :: Python :: 3
Classifier: License :: OSI Approved :: MIT License
Classifier: Operating System :: OS Independent
Requires-Python: >=3.6
License-File: LICENSE
Requires-Dist: numpy
Requires-Dist: tqdm
Requires-Dist: logging
